bulksmsmd/__init__.py
bulksmsmd/client.py
bulksmsmd-0.1.3.dist-info/LICENSE
bulksmsmd-0.1.3.dist-info/METADATA
bulksmsmd-0.1.3.dist-info/WHEEL
bulksmsmd-0.1.3.dist-info/top_level.txt
bulksmsmd-0.1.3.dist-info/RECORD
