Metadata-Version: 2.1
Name: bulksmsmd
Version: 0.1.3
Summary: Python wrapper for Unifun BulkSMSAPI (bulksms.md)
Home-page: https://github.com/markmelnic/bulksmsmd
Author: Mark Melnic
Author-email: me@markmelnic.com
License: MIT
Keywords: python api wrapper unifun bulksms bulksmsmd bulksmsapi
Classifier: Natural Language :: English
Classifier: Development Status :: 5 - Production/Stable
Classifier: Intended Audience :: Developers
Classifier: License :: OSI Approved :: MIT License
Classifier: Programming Language :: Python :: 3
Classifier: Programming Language :: Python :: 3.6
Classifier: Programming Language :: Python :: 3.7
Classifier: Programming Language :: Python :: 3.8
Classifier: Programming Language :: Python :: 3.9
Classifier: Programming Language :: Python :: 3.10
Classifier: Programming Language :: Python :: 3.11
Classifier: Programming Language :: Python :: 3.12
License-File: LICENSE
Requires-Dist: requests
